fds/__init__.py
fds/sdk/__init__.py
fds/sdk/CapitalStructureReportBuilder/__init__.py
fds/sdk/CapitalStructureReportBuilder/api_client.py
fds/sdk/CapitalStructureReportBuilder/configuration.py
fds/sdk/CapitalStructureReportBuilder/exceptions.py
fds/sdk/CapitalStructureReportBuilder/model_utils.py
fds/sdk/CapitalStructureReportBuilder/rest.py
fds/sdk/CapitalStructureReportBuilder/api/__init__.py
fds/sdk/CapitalStructureReportBuilder/api/capital_structure_api.py
fds/sdk/CapitalStructureReportBuilder/apis/__init__.py
fds/sdk/CapitalStructureReportBuilder/model/__init__.py
fds/sdk/CapitalStructureReportBuilder/model/error_object.py
fds/sdk/CapitalStructureReportBuilder/model/error_object_links.py
fds/sdk/CapitalStructureReportBuilder/model/error_object_source.py
fds/sdk/CapitalStructureReportBuilder/model/error_response.py
fds/sdk/CapitalStructureReportBuilder/model/meta.py
fds/sdk/CapitalStructureReportBuilder/model/response.py
fds/sdk/CapitalStructureReportBuilder/models/__init__.py
fds.sdk.CapitalStructureReportBuilder-1.0.14.dist-info/LICENSE
fds.sdk.CapitalStructureReportBuilder-1.0.14.dist-info/METADATA
fds.sdk.CapitalStructureReportBuilder-1.0.14.dist-info/WHEEL
fds.sdk.CapitalStructureReportBuilder-1.0.14.dist-info/top_level.txt
fds.sdk.CapitalStructureReportBuilder-1.0.14.dist-info/RECORD
